async_lm/__init__.py
async_lm-0.0.1.dist-info/LICENSE
async_lm-0.0.1.dist-info/METADATA
async_lm-0.0.1.dist-info/WHEEL
async_lm-0.0.1.dist-info/top_level.txt
async_lm-0.0.1.dist-info/RECORD
